ALU_nonclk/alu.v
/* ALU Arithmetic and Logic Operations
----------------------------------------------------------------------
|ALU_Sel|   ALU Operation
----------------------------------------------------------------------
| 0000  |   ALU_Out = A + B;
----------------------------------------------------------------------
| 0001  |   ALU_Out = A - B;
----------------------------------------------------------------------
| 0010  |   ALU_Out = A * B;
----------------------------------------------------------------------
| 0011  |   ALU_Out = A / B;
----------------------------------------------------------------------
| 0100  |   ALU_Out = A << 1;
----------------------------------------------------------------------
| 0101  |   ALU_Out = A >> 1;
----------------------------------------------------------------------
| 0110  |   ALU_Out = A rotated left by 1;
----------------------------------------------------------------------
| 0111  |   ALU_Out = A rotated right by 1;
----------------------------------------------------------------------
| 1000  |   ALU_Out = A and B;
----------------------------------------------------------------------
| 1001  |   ALU_Out = A or B;
----------------------------------------------------------------------
| 1010  |   ALU_Out = A xor B;
----------------------------------------------------------------------
| 1011  |   ALU_Out = A nor B;
----------------------------------------------------------------------
| 1100  |   ALU_Out = A nand B;
----------------------------------------------------------------------
| 1101  |   ALU_Out = A xnor B;
----------------------------------------------------------------------
| 1110  |   ALU_Out = 1 if A>B else 0;
----------------------------------------------------------------------
| 1111  |   ALU_Out = 1 if A=B else 0;
----------------------------------------------------------------------*/

module alu(
            input [1:0] A,B,  // ALU 8-bit Inputs                 
            input [3:0] ALU_Sel,// ALU Selection
            output [7:0] ALU_Out, // ALU 8-bit Output
            output CarryOut // Carry Out Flag
    );
    reg [7:0] ALU_Result;
    wire [8:0] tmp;
    assign tmp = {1'b0,A} + {1'b0,B};
    assign CarryOut = tmp[8]; // Carryout flag
    always @(*)
    begin
        case(ALU_Sel)
        4'b0000: // Addition
           ALU_Result = A + B ; 
        4'b0001: // Subtraction
           ALU_Result = A - B ;
        4'b0010: // Multiplication
           ALU_Result = A * B;
        4'b0011: // Division
           ALU_Result = A/B;
        4'b0100: // Logical shift left
           ALU_Result = A<<1;
        4'b0101: // Logical shift right
           ALU_Result = A>>1;
        4'b0110: // Rotate left
           ALU_Result = {A[0],A[1]};
        4'b0111: // Rotate right
           ALU_Result = {A[0],A[1]};
        4'b1000: //  Logical and 
           ALU_Result = A & B;
        4'b1001: //  Logical or
           ALU_Result = A | B;
        4'b1010: //  Logical xor 
           ALU_Result = A ^ B;
        4'b1011: //  Logical nor
           ALU_Result = ~(A | B);
        4'b1100: // Logical nand 
           ALU_Result = ~(A & B);
        4'b1101: // Logical xnor
           ALU_Result = ~(A ^ B);
        4'b1110: // Greater comparison
           ALU_Result = (A>B)?8'd1:8'd0 ;
        4'b1111: // Equal comparison   
            ALU_Result = (A==B)? 8'd1:8'd0 ;
          default: ALU_Result = A + B ; 
        endcase
    end
    assign ALU_Out = ALU_Result; // ALU out

endmodule

ALU_nonclk/alu_tb.v
// ALU testbench
`timescale 1ns / 1ps  

module alu_tb;
//Inputs
 reg[1:0] A,B;
 reg[3:0] ALU_Sel;

//Outputs
 wire[7:0] ALU_Out;
 wire CarryOut;
 // Verilog code for ALU
 integer i;
 alu test_unit(
            A,B,  // ALU 8-bit Inputs                 
            ALU_Sel,// ALU Selection
            ALU_Out, // ALU 8-bit Output
            CarryOut // Carry Out Flag
     );

initial begin
    $dumpfile("alu_tb.vcd");
    $dumpvars(0,alu_tb);
// hold reset state for 100 ns.
    A = 2'h3;
    B = 2'h1;
    ALU_Sel = 4'h0;
    
    for (i=0;i<=15;i=i+1)
    begin
    ALU_Sel = ALU_Sel + 4'h01;
    #20;
    end;
    $finish; 
end

endmodule

ALU_nonclk/alu_tb.vcd
$date
	Thu Mar 16 21:59:51 2023
$end
$version
	Icarus Verilog
$end
$timescale
	1ps
$end
$scope module alu_tb $end
$var wire 1 ! CarryOut $end
$var wire 8 " ALU_Out [7:0] $end
$var reg 2 # A [1:0] $end
$var reg 4 $ ALU_Sel [3:0] $end
$var reg 2 % B [1:0] $end
$var integer 32 & i [31:0] $end
$scope module test_unit $end
$var wire 2 ' A [1:0] $end
$var wire 8 ( ALU_Out [7:0] $end
$var wire 4 ) ALU_Sel [3:0] $end
$var wire 2 * B [1:0] $end
$var wire 9 + tmp [8:0] $end
$var wire 1 ! CarryOut $end
$var reg 8 , ALU_Result [7:0] $end
$upscope $end
$upscope $end
$enddefinitions $end
$comment Show the parameter values. $end
$dumpall
$end
#0
$dumpvars
b10 ,
b100 +
b1 *
b1 )
b10 (
b11 '
b0 &
b1 %
b1 $
b11 #
b10 "
0!
$end
#20000
b11 "
b11 (
b11 ,
b10 $
b10 )
b1 &
#40000
b11 $
b11 )
b10 &
#60000
b110 "
b110 (
b110 ,
b100 $
b100 )
b11 &
#80000
b1 "
b1 (
b1 ,
b101 $
b101 )
b100 &
#100000
b11 "
b11 (
b11 ,
b110 $
b110 )
b101 &
#120000
b111 $
b111 )
b110 &
#140000
b1 "
b1 (
b1 ,
b1000 $
b1000 )
b111 &
#160000
b11 "
b11 (
b11 ,
b1001 $
b1001 )
b1000 &
#180000
b10 "
b10 (
b10 ,
b1010 $
b1010 )
b1001 &
#200000
b11111100 "
b11111100 (
b11111100 ,
b1011 $
b1011 )
b1010 &
#220000
b11111110 "
b11111110 (
b11111110 ,
b1100 $
b1100 )
b1011 &
#240000
b11111101 "
b11111101 (
b11111101 ,
b1101 $
b1101 )
b1100 &
#260000
b1 "
b1 (
b1 ,
b1110 $
b1110 )
b1101 &
#280000
b0 "
b0 (
b0 ,
b1111 $
b1111 )
b1110 &
#300000
b100 "
b100 (
b100 ,
b0 $
b0 )
b1111 &
#320000
b10000 &
