RISC_16bit_core/Parameter.v
`ifndef PARAMETER_H_
`define PARAMETER_H_
// Verilog code for RISC Processor 
// Parameter file
`define col 16 // 16 bits instruction memory, data memory
`define row_i 15 // instruction memory, instructions number, this number can be changed. Adding more instructions to verify your design is a good idea.
`define row_d 8 // The number of data in data memory. We only use 8 data. Do not change this number. You can change the value of each data inside test.data file. Total number is fixed at 8. 
`define filename "output.txt"
`define simulation_time #100

`endif

RISC_16bit_core/src/Control_Unit.v
// Verilog code for RISC Processor 
// Verilog code for Control Unit
`timescale 1ns / 1ps
 
module Control_Unit(
      input[3:0] opcode,
      output reg[1:0] alu_op,
      output reg jump,beq,bne,mem_read,mem_write,alu_src,reg_dst,mem_to_reg,reg_write    
    );


always @(*)
begin
 case(opcode) 
 4'b0000:  // LW
   begin
    reg_dst = 1'b0;
    alu_src = 1'b1;
    mem_to_reg = 1'b1;
    reg_write = 1'b1;
    mem_read = 1'b1;
    mem_write = 1'b0;
    beq = 1'b0;
    bne = 1'b0;
    alu_op = 2'b10;
    jump = 1'b0;   
   end
 4'b0001:  // SW
   begin
    reg_dst = 1'b0;
    alu_src = 1'b1;
    mem_to_reg = 1'b0;
    reg_write = 1'b0;
    mem_read = 1'b0;
    mem_write = 1'b1;
    beq = 1'b0;
    bne = 1'b0;
    alu_op = 2'b10;
    jump = 1'b0;   
   end
 4'b0010:  // data_processing
   begin
    reg_dst = 1'b1;
    alu_src = 1'b0;
    mem_to_reg = 1'b0;
    reg_write = 1'b1;
    mem_read = 1'b0;
    mem_write = 1'b0;
    beq = 1'b0;
    bne = 1'b0;
    alu_op = 2'b00;
    jump = 1'b0;   
   end
 4'b0011:  // data_processing
   begin
    reg_dst = 1'b1;
    alu_src = 1'b0;
    mem_to_reg = 1'b0;
    reg_write = 1'b1;
    mem_read = 1'b0;
    mem_write = 1'b0;
    beq = 1'b0;
    bne = 1'b0;
    alu_op = 2'b00;
    jump = 1'b0;   
   end
 4'b0100:  // data_processing
   begin
    reg_dst = 1'b1;
    alu_src = 1'b0;
    mem_to_reg = 1'b0;
    reg_write = 1'b1;
    mem_read = 1'b0;
    mem_write = 1'b0;
    beq = 1'b0;
    bne = 1'b0;
    alu_op = 2'b00;
    jump = 1'b0;   
   end
 4'b0101:  // data_processing
   begin
    reg_dst = 1'b1;
    alu_src = 1'b0;
    mem_to_reg = 1'b0;
    reg_write = 1'b1;
    mem_read = 1'b0;
    mem_write = 1'b0;
    beq = 1'b0;
    bne = 1'b0;
    alu_op = 2'b00;
    jump = 1'b0;   
   end
 4'b0110:  // data_processing
   begin
    reg_dst = 1'b1;
    alu_src = 1'b0;
    mem_to_reg = 1'b0;
    reg_write = 1'b1;
    mem_read = 1'b0;
    mem_write = 1'b0;
    beq = 1'b0;
    bne = 1'b0;
    alu_op = 2'b00;
    jump = 1'b0;   
   end
 4'b0111:  // data_processing
   begin
    reg_dst = 1'b1;
    alu_src = 1'b0;
    mem_to_reg = 1'b0;
    reg_write = 1'b1;
    mem_read = 1'b0;
    mem_write = 1'b0;
    beq = 1'b0;
    bne = 1'b0;
    alu_op = 2'b00;
    jump = 1'b0;   
   end
 4'b1000:  // data_processing
   begin
    reg_dst = 1'b1;
    alu_src = 1'b0;
    mem_to_reg = 1'b0;
    reg_write = 1'b1;
    mem_read = 1'b0;
    mem_write = 1'b0;
    beq = 1'b0;
    bne = 1'b0;
    alu_op = 2'b00;
    jump = 1'b0;   
   end
 4'b1001:  // data_processing
   begin
    reg_dst = 1'b1;
    alu_src = 1'b0;
    mem_to_reg = 1'b0;
    reg_write = 1'b1;
    mem_read = 1'b0;
    mem_write = 1'b0;
    beq = 1'b0;
    bne = 1'b0;
    alu_op = 2'b00;
    jump = 1'b0;   
   end
 4'b1011:  // BEQ
   begin
    reg_dst = 1'b0;
    alu_src = 1'b0;
    mem_to_reg = 1'b0;
    reg_write = 1'b0;
    mem_read = 1'b0;
    mem_write = 1'b0;
    beq = 1'b1;
    bne = 1'b0;
    alu_op = 2'b01;
    jump = 1'b0;   
   end
 4'b1100:  // BNE
   begin
    reg_dst = 1'b0;
    alu_src = 1'b0;
    mem_to_reg = 1'b0;
    reg_write = 1'b0;
    mem_read = 1'b0;
    mem_write = 1'b0;
    beq = 1'b0;
    bne = 1'b1;
    alu_op = 2'b01;
    jump = 1'b0;   
   end
 4'b1101:  // J
   begin
    reg_dst = 1'b0;
    alu_src = 1'b0;
    mem_to_reg = 1'b0;
    reg_write = 1'b0;
    mem_read = 1'b0;
    mem_write = 1'b0;
    beq = 1'b0;
    bne = 1'b0;
    alu_op = 2'b00;
    jump = 1'b1;   
   end   
 default: begin
    reg_dst = 1'b1;
    alu_src = 1'b0;
    mem_to_reg = 1'b0;
    reg_write = 1'b1;
    mem_read = 1'b0;
    mem_write = 1'b0;
    beq = 1'b0;
    bne = 1'b0;
    alu_op = 2'b00;
    jump = 1'b0; 
   end
 endcase
 end

endmodule

RISC_16bit_core/Data_Memory.v
`include "Parameter.v"
// fpga4student.com 
// FPGA projects, VHDL projects, Verilog projects 
// Verilog code for RISC Processor 
// Verilog code for data Memory
module Data_Memory(
 input clk,
 // address input, shared by read and write port
 input [15:0]   mem_access_addr,
 
 // write port
 input [15:0]   mem_write_data,
 input     mem_write_en,
 input mem_read,
 // read port
 output [15:0]   mem_read_data
);

reg [0:`col - 1] memory [0:`row_d - 1];
integer f;
wire [2:0] ram_addr=mem_access_addr[2:0];
initial
 begin
  $readmemb("test.data", memory);
  // f = $fopen(`filename);
  $monitor("\ntime = %d\n", $time, 
  "\tmemory[0] = %b\n", memory[0],   
  "\tmemory[1] = %b\n", memory[1],
  "\tmemory[2] = %b\n", memory[2],
  "\tmemory[3] = %b\n", memory[3],
  "\tmemory[4] = %b\n", memory[4],
  "\tmemory[5] = %b\n", memory[5],
  "\tmemory[6] = %b\n", memory[6],
  "\tmemory[7] = %b\n", memory[7]);
  #10;
  // $fclose(f);
 end
 
 always @(posedge clk) begin
  if (mem_write_en)
   memory[ram_addr] <= mem_write_data;
 end
 assign mem_read_data = (mem_read==1'b1) ? memory[ram_addr]: 16'd0; 

endmodule

RISC_16bit_core/ALU.v
// Verilog code for RISC Processor 
// Verilog code for ALU
module ALU(
 input  [15:0] a,  //src1
 input  [15:0] b,  //src2
 input  [2:0] alu_control, //function sel
 
 output reg [15:0] result,  //result 
 output zero
    );

always @(*)
begin 
 case(alu_control)
 3'b000: result = a + b; // add
 3'b001: result = a - b; // sub
 3'b010: result = ~a;
 3'b011: result = a<<b;
 3'b100: result = a>>b;
 3'b101: result = a & b; // and
 3'b110: result = a | b; // or
 3'b111: begin if (a<b) result = 16'd1;
    else result = 16'd0;
    end
 default:result = a + b; // add
 endcase
end
assign zero = (result==16'd0) ? 1'b1: 1'b0;
 
endmodule

RISC_16bit_core/src/alu_control.v
// Verilog code for 16-bit RISC processor
// ALU_Control Verilog code
`timescale 1ns / 1ps

module alu_control( ALU_Cnt, ALUOp, Opcode);
 output reg[2:0] ALU_Cnt;
 input [1:0] ALUOp;
 input [3:0] Opcode;
 wire [5:0] ALUControlIn;
 assign ALUControlIn = {ALUOp,Opcode};
 always @(ALUControlIn)
 casex (ALUControlIn)
   6'b10xxxx: ALU_Cnt=3'b000;
   6'b01xxxx: ALU_Cnt=3'b001;
   6'b000010: ALU_Cnt=3'b000;
   6'b000011: ALU_Cnt=3'b001;
   6'b000100: ALU_Cnt=3'b010;
   6'b000101: ALU_Cnt=3'b011;
   6'b000110: ALU_Cnt=3'b100;
   6'b000111: ALU_Cnt=3'b101;
   6'b001000: ALU_Cnt=3'b110;
   6'b001001: ALU_Cnt=3'b111;
  default: ALU_Cnt=3'b000;
  endcase
endmodule

RISC_16bit_core/src/GPRs.v
// Verilog code for RISC Processor 
// Verilog code for register file
`timescale 1ns / 1ps 

module GPRs(
 input    clk,
 // write port
 input    reg_write_en,
 input  [2:0] reg_write_dest,
 input  [15:0] reg_write_data,
 //read port 1
 input  [2:0] reg_read_addr_1,
 output  [15:0] reg_read_data_1,
 //read port 2
 input  [2:0] reg_read_addr_2,
 output  [15:0] reg_read_data_2
);
 reg [15:0] reg_array [7:0];
 integer i;
 // write port
 //reg [2:0] i;
 initial begin
  for(i=0;i<8;i=i+1)
   reg_array[i] <= 16'd0;
 end
 always @ (posedge clk ) begin
   if(reg_write_en) begin
    reg_array[reg_write_dest] <= reg_write_data;
   end
 end
 

 assign reg_read_data_1 = reg_array[reg_read_addr_1];
 assign reg_read_data_2 = reg_array[reg_read_addr_2];


endmodule

RISC_16bit_core/Instruction_Memory.v
// Verilog code for RISC Processor 
// Verilog code for Instruction Memory

`include "Parameter.v"

module Instruction_Memory(
 input[15:0] pc,
 output[15:0] instruction
);

 reg [0:`col - 1] memory [0:`row_i - 1];
 wire [3 : 0] rom_addr = pc[4 : 1];
 initial
 begin
  $readmemb("test.prog", memory,0,14);
 end
 assign instruction =  memory[rom_addr]; 

endmodule

RISC_16bit_core/src/Datapath_Unit.v
// Verilog code for RISC Processor 
// Verilog code for Data Path of the processor
`timescale 1ns / 1ps
`include "src/Instruction_Memory.v"
`include "src/GPRs.v"
`include "src/alu_control.v"
`include "src/ALU.v"
`include "src/Data_Memory.v"

module Datapath_Unit(
 input clk,
 input jump,beq,mem_read,mem_write,alu_src,reg_dst,mem_to_reg,reg_write,bne,
 input[1:0] alu_op,
 output[3:0] opcode
);
 reg  [15:0] pc_current;
 wire [15:0] pc_next,pc2;
 wire [15:0] instr;
 wire [2:0] reg_write_dest;
 wire [15:0] reg_write_data;
 wire [2:0] reg_read_addr_1;
 wire [15:0] reg_read_data_1;
 wire [2:0] reg_read_addr_2;
 wire [15:0] reg_read_data_2;
 wire [15:0] ext_im,read_data2;
 wire [2:0] ALU_Control;
 wire [15:0] ALU_out;
 wire zero_flag;
 wire [15:0] PC_j, PC_beq, PC_2beq,PC_2bne,PC_bne;
 wire beq_control;
 wire [12:0] jump_shift;
 wire [15:0] mem_read_data;
 // PC 
 initial begin
  pc_current <= 16'd0;
 end
 always @(posedge clk)
 begin 
   pc_current <= pc_next;
 end
 assign pc2 = pc_current + 16'd2;
 // instruction memory
 Instruction_Memory im(.pc(pc_current),.instruction(instr));
 // jump shift left 2
 assign jump_shift = {instr[11:0],1'b0};
 // multiplexer regdest
 assign reg_write_dest = (reg_dst==1'b1) ? instr[5:3] :instr[8:6];
 // register file
 assign reg_read_addr_1 = instr[11:9];
 assign reg_read_addr_2 = instr[8:6];

 // GENERAL PURPOSE REGISTERs
 GPRs reg_file
 (
  .clk(clk),
  .reg_write_en(reg_write),
  .reg_write_dest(reg_write_dest),
  .reg_write_data(reg_write_data),
  .reg_read_addr_1(reg_read_addr_1),
  .reg_read_data_1(reg_read_data_1),
  .reg_read_addr_2(reg_read_addr_2),
  .reg_read_data_2(reg_read_data_2)
 );
 // immediate extend
 assign ext_im = {{10{instr[5]}},instr[5:0]};  
 // ALU control unit
 alu_control ALU_Control_unit(.ALUOp(alu_op),.Opcode(instr[15:12]),.ALU_Cnt(ALU_Control));
 // multiplexer alu_src
 assign read_data2 = (alu_src==1'b1) ? ext_im : reg_read_data_2;
 // ALU 
 ALU alu_unit(.a(reg_read_data_1),.b(read_data2),.alu_control(ALU_Control),.result(ALU_out),.zero(zero_flag));
 // PC beq add
 assign PC_beq = pc2 + {ext_im[14:0],1'b0};
 assign PC_bne = pc2 + {ext_im[14:0],1'b0};
 // beq control
 assign beq_control = beq & zero_flag;
 assign bne_control = bne & (~zero_flag);
 // PC_beq
 assign PC_2beq = (beq_control==1'b1) ? PC_beq : pc2;
 // PC_bne
 assign PC_2bne = (bne_control==1'b1) ? PC_bne : PC_2beq;
 // PC_j
 assign PC_j = {pc2[15:13],jump_shift};
 // PC_next
 assign pc_next = (jump == 1'b1) ? PC_j :  PC_2bne;

 /// Data memory
  Data_Memory dm
   (
    .clk(clk),
    .mem_access_addr(ALU_out),
    .mem_write_data(reg_read_data_2),
    .mem_write_en(mem_write),
    .mem_read(mem_read),
    .mem_read_data(mem_read_data)
   );
 
 // write back
 assign reg_write_data = (mem_to_reg == 1'b1)?  mem_read_data: ALU_out;
 // output to control unit
 assign opcode = instr[15:12];
endmodule

RISC_16bit_core/src/Risc_16_bit.v
`timescale 1ns / 1ps
// FPGA projects, VHDL projects, Verilog projects 
// Verilog code for RISC Processor 
`include "Datapath_Unit.v"
`include "Control_Unit.v"
module Risc_16_bit(
 input clk
);
 wire jump,bne,beq,mem_read,mem_write,alu_src,reg_dst,mem_to_reg,reg_write;
 wire[1:0] alu_op;
 wire [3:0] opcode;
 // Datapath
 Datapath_Unit DU
 (
  .clk(clk),
  .jump(jump),
  .beq(beq),
  .mem_read(mem_read),
  .mem_write(mem_write),
  .alu_src(alu_src),
  .reg_dst(reg_dst),
  .mem_to_reg(mem_to_reg),
  .reg_write(reg_write),
  .bne(bne),
  .alu_op(alu_op),
  .opcode(opcode)
 );
 // control unit
 Control_Unit control
 (
  .opcode(opcode),
  .reg_dst(reg_dst),
  .mem_to_reg(mem_to_reg),
  .alu_op(alu_op),
  .jump(jump),
  .bne(bne),
  .beq(beq),
  .mem_read(mem_read),
  .mem_write(mem_write),
  .alu_src(alu_src),
  .reg_write(reg_write)
 );

endmodule

RISC_16bit_core/tb/main_tb.v
`timescale 1ns / 1ps
`include "src/Parameter.v"

module test_Risc_16_bit;

 // Inputs
 reg clk;

 // Instantiate the Unit Under Test (UUT)
 Risc_16_bit uut (
  .clk(clk)
 );

 initial 
  begin
    $dumpfile("dump.vcd"); 
    $dumpvars;
   clk <=0;
   `simulation_time;
   $finish;
  end

 always 
  begin
   #5 clk = ~clk;
  end

endmodule

RISC_16bit_core/dump.vcd
$date
	Fri Apr 21 15:31:39 2023
$end
$version
	Icarus Verilog
$end
$timescale
	1ps
$end
$scope module test_Risc_16_bit $end
$var reg 1 ! clk $end
$scope module uut $end
$var wire 1 ! clk $end
$var wire 1 " reg_write $end
$var wire 1 # reg_dst $end
$var wire 4 $ opcode [3:0] $end
$var wire 1 % mem_write $end
$var wire 1 & mem_to_reg $end
$var wire 1 ' mem_read $end
$var wire 1 ( jump $end
$var wire 1 ) bne $end
$var wire 1 * beq $end
$var wire 1 + alu_src $end
$var wire 2 , alu_op [1:0] $end
$scope module DU $end
$var wire 1 - beq_control $end
$var wire 1 . bne_control $end
$var wire 1 ! clk $end
$var wire 1 / zero_flag $end
$var wire 3 0 reg_write_dest [2:0] $end
$var wire 16 1 reg_write_data [15:0] $end
$var wire 1 " reg_write $end
$var wire 16 2 reg_read_data_2 [15:0] $end
$var wire 16 3 reg_read_data_1 [15:0] $end
$var wire 3 4 reg_read_addr_2 [2:0] $end
$var wire 3 5 reg_read_addr_1 [2:0] $end
$var wire 1 # reg_dst $end
$var wire 16 6 read_data2 [15:0] $end
$var wire 16 7 pc_next [15:0] $end
$var wire 16 8 pc2 [15:0] $end
$var wire 4 9 opcode [3:0] $end
$var wire 1 % mem_write $end
$var wire 1 & mem_to_reg $end
$var wire 16 : mem_read_data [15:0] $end
$var wire 1 ' mem_read $end
$var wire 13 ; jump_shift [12:0] $end
$var wire 1 ( jump $end
$var wire 16 < instr [15:0] $end
$var wire 16 = ext_im [15:0] $end
$var wire 1 ) bne $end
$var wire 1 * beq $end
$var wire 1 + alu_src $end
$var wire 2 > alu_op [1:0] $end
$var wire 16 ? PC_j [15:0] $end
$var wire 16 @ PC_bne [15:0] $end
$var wire 16 A PC_beq [15:0] $end
$var wire 16 B PC_2bne [15:0] $end
$var wire 16 C PC_2beq [15:0] $end
$var wire 16 D ALU_out [15:0] $end
$var wire 3 E ALU_Control [2:0] $end
$var reg 16 F pc_current [15:0] $end
$scope module ALU_Control_unit $end
$var wire 4 G Opcode [3:0] $end
$var wire 2 H ALUOp [1:0] $end
$var wire 6 I ALUControlIn [5:0] $end
$var reg 3 J ALU_Cnt [2:0] $end
$upscope $end
$scope module alu_unit $end
$var wire 3 K alu_control [2:0] $end
$var wire 16 L b [15:0] $end
$var wire 1 / zero $end
$var wire 16 M a [15:0] $end
$var reg 16 N result [15:0] $end
$upscope $end
$scope module dm $end
$var wire 1 ! clk $end
$var wire 16 O mem_access_addr [15:0] $end
$var wire 3 P ram_addr [2:0] $end
$var wire 1 % mem_write_en $end
$var wire 16 Q mem_write_data [15:0] $end
$var wire 16 R mem_read_data [15:0] $end
$var wire 1 ' mem_read $end
$upscope $end
$scope module im $end
$var wire 16 S instruction [15:0] $end
$var wire 16 T pc [15:0] $end
$var wire 4 U rom_addr [3:0] $end
$upscope $end
$scope module reg_file $end
$var wire 1 ! clk $end
$var wire 3 V reg_read_addr_1 [2:0] $end
$var wire 3 W reg_read_addr_2 [2:0] $end
$var wire 16 X reg_read_data_1 [15:0] $end
$var wire 16 Y reg_read_data_2 [15:0] $end
$var wire 16 Z reg_write_data [15:0] $end
$var wire 3 [ reg_write_dest [2:0] $end
$var wire 1 " reg_write_en $end
$var integer 32 \ i [31:0] $end
$upscope $end
$upscope $end
$scope module control $end
$var wire 4 ] opcode [3:0] $end
$var reg 2 ^ alu_op [1:0] $end
$var reg 1 + alu_src $end
$var reg 1 * beq $end
$var reg 1 ) bne $end
$var reg 1 ( jump $end
$var reg 1 ' mem_read $end
$var reg 1 & mem_to_reg $end
$var reg 1 % mem_write $end
$var reg 1 # reg_dst $end
$var reg 1 " reg_write $end
$upscope $end
$upscope $end
$upscope $end
$enddefinitions $end
$comment Show the parameter values. $end
$dumpall
$end
#0
$dumpvars
b10 ^
b0 ]
b1000 \
b0 [
b1 Z
b0 Y
b0 X
b0 W
b10 V
b0 U
b0 T
b10000000000 S
b1 R
b0 Q
b0 P
b0 O
b0 N
b0 M
b0 L
b0 K
b0 J
b100000 I
b10 H
b0 G
b0 F
b0 E
b0 D
b10 C
b10 B
b10 A
b10 @
b100000000000 ?
b10 >
b0 =
b10000000000 <
b100000000000 ;
b1 :
b0 9
b10 8
b10 7
b0 6
b10 5
b0 4
b0 3
b0 2
b1 1
b0 0
1/
0.
0-
b10 ,
1+
0*
0)
0(
1'
1&
0%
b0 $
0#
1"
0!
$end
#5000
b10 1
b10 Z
b10 :
b10 R
0/
b1 P
b1 D
b1 N
b1 O
b100 7
b1 6
b1 L
b1 0
b1 [
b100 B
b1 =
b1 4
b1 W
b100010000010 ?
b100010000010 ;
b100 C
b10001000001 <
b10001000001 S
b1 U
b0 2
b0 Q
b0 Y
b110 A
b110 @
b100 8
b10 F
b10 T
1!
#10000
0!
#15000
b11 1
b11 Z
b10 0
b10 [
b0 :
b0 R
b11 P
b110 7
b0 ,
b0 >
b0 H
b0 ^
0'
0&
0+
1#
b10 6
b10 L
b11 D
b11 N
b11 O
b110 B
b10 $
b10 9
b10 ]
b10 I
b10 G
b10000 =
b1 3
b1 M
b1 X
b0 5
b0 V
b10100000 ?
b10100000 ;
b110 C
b10000001010000 <
b10000001010000 S
b10 U
b100110 A
b100110 @
b110 8
b100 F
b100 T
b10 2
b10 Q
b10 Y
1!
#20000
0!
#25000
b10 P
b10 1
b10 Z
b1000 7
b10 ,
b10 >
b10 H
b10 ^
1%
0"
1+
0#
b0 6
b0 L
b10 D
b10 N
b10 O
b10 0
b10 [
b1000 B
b1 $
b1 9
b1 ]
b100001 I
b1 G
b0 =
b11 2
b11 Q
b11 Y
b10 4
b10 W
b10 3
b10 M
b10 X
b1 5
b1 V
b10100000000 ?
b10100000000 ;
b1000 C
b1001010000000 <
b1001010000000 S
b11 U
b1000 A
b1000 @
b1000 8
b110 F
b110 T
1!
#30000
0!
#35000
b1 E
b1 J
b1 K
b111 P
b1111111111111111 1
b1111111111111111 Z
b1010 7
b0 ,
b0 >
b0 H
b0 ^
0%
1"
0+
1#
b10 6
b10 L
b1111111111111111 D
b1111111111111111 N
b1111111111111111 O
b10 0
b10 [
b1010 B
b11 $
b11 9
b11 ]
b11 I
b11 G
b10000 =
b10 2
b10 Q
b10 Y
b1 4
b1 W
b1 3
b1 M
b1 X
b0 5
b0 V
b10100000 ?
b10100000 ;
b1010 C
b11000001010000 <
b11000001010000 S
b100 U
b101010 A
b101010 @
b1010 8
b1000 F
b1000 T
1!
#40000
0!
#45000
b110 P
b1111111111111110 1
b1111111111111110 Z
b1111111111111110 D
b1111111111111110 N
b1111111111111110 O
b1100 7
b10 E
b10 J
b10 K
b1100 B
b100 $
b100 9
b100 ]
b100 I
b100 G
b1100 C
b100000001010000 <
b100000001010000 S
b101 U
b101100 A
b101100 @
b1100 8
b1010 F
b1010 T
1!
#50000
0!
#55000
b100 P
b100 1
b100 Z
b100 D
b100 N
b100 O
b1110 7
b11 E
b11 J
b11 K
b1110 B
b101 $
b101 9
b101 ]
b101 I
b101 G
b1110 C
b101000001010000 <
b101000001010000 S
b110 U
b101110 A
b101110 @
b1110 8
b1100 F
b1100 T
1!
#60000
0!
#65000
1/
b0 P
b0 1
b0 Z
b0 D
b0 N
b0 O
b10000 7
b100 E
b100 J
b100 K
b10000 B
b110 $
b110 9
b110 ]
b110 I
b110 G
b10000 C
b110000001010000 <
b110000001010000 S
b111 U
b110000 A
b110000 @
b10000 8
b1110 F
b1110 T
1!
#70000
0!
#75000
b10010 7
b101 E
b101 J
b101 K
b10010 B
b111 $
b111 9
b111 ]
b111 I
b111 G
b10010 C
b111000001010000 <
b111000001010000 S
b1000 U
b110010 A
b110010 @
b10010 8
b10000 F
b10000 T
1!
#80000
0!
#85000
0/
b11 P
b11 1
b11 Z
b11 D
b11 N
b11 O
b10100 7
b110 E
b110 J
b110 K
b10100 B
b1000 $
b1000 9
b1000 ]
b1000 I
b1000 G
b10100 C
b1000000001010000 <
b1000000001010000 S
b1001 U
b110100 A
b110100 @
b10100 8
b10010 F
b10010 T
1!
#90000
0!
#95000
b1 P
b1 1
b1 Z
b1 D
b1 N
b1 O
b10110 7
b111 E
b111 J
b111 K
b10110 B
b1001 $
b1001 9
b1001 ]
b1001 I
b1001 G
b10110 C
b1001000001010000 <
b1001000001010000 S
b1010 U
b110110 A
b110110 @
b10110 8
b10100 F
b10100 T
1!
