ALU_32bit/alu_32bit.v
/* ALU Arithmetic and Logic Operations
----------------------------------------------------------------------
|ALU_Sel|   ALU Operation
----------------------------------------------------------------------
| 0000  |   ALU_Out = A + B;
----------------------------------------------------------------------
| 0001  |   ALU_Out = A - B;
----------------------------------------------------------------------
| 0010  |   ALU_Out = A * B;
----------------------------------------------------------------------
| 0011  |   ALU_Out = A / B;
----------------------------------------------------------------------
| 0100  |   ALU_Out = A << 1;
----------------------------------------------------------------------
| 0101  |   ALU_Out = A >> 1;
----------------------------------------------------------------------
| 0110  |   ALU_Out = A rotated left by 1;
----------------------------------------------------------------------
| 0111  |   ALU_Out = A rotated right by 1;
----------------------------------------------------------------------
| 1000  |   ALU_Out = A and B;
----------------------------------------------------------------------
| 1001  |   ALU_Out = A or B;
----------------------------------------------------------------------
| 1010  |   ALU_Out = A xor B;
----------------------------------------------------------------------
| 1011  |   ALU_Out = A nor B;
----------------------------------------------------------------------
| 1100  |   ALU_Out = A nand B;
----------------------------------------------------------------------
| 1101  |   ALU_Out = A xnor B;
----------------------------------------------------------------------
| 1110  |   ALU_Out = 1 if A>B else 0;
----------------------------------------------------------------------
| 1111  |   ALU_Out = 1 if A=B else 0;
----------------------------------------------------------------------*/

module alu(
            input clk,
            input [31:0] A,B,  // ALU 8-bit Inputs                 
            input [3:0] ALU_Sel,// ALU Selection
            output [31:0] ALU_Out, // ALU 8-bit Output
            output CarryOut // Carry Out Flag
    );
    reg [31:0] ALU_Result;
    wire [32:0] tmp;
    assign tmp = {1'b0,A} + {1'b0,B};
    assign CarryOut = tmp[8]; // Carryout flag
    always @(posedge clk)
    begin
        case(ALU_Sel)
        4'b0000: // Addition
           ALU_Result = A + B ; 
        4'b0001: // Subtraction
           ALU_Result = A - B ;
        4'b0010: // Multiplication
           ALU_Result = A * B;
        4'b0011: // Division
           ALU_Result = A/B;
        4'b0100: // Logical shift left
           ALU_Result = A<<1;
        4'b0101: // Logical shift right
           ALU_Result = A>>1;
        4'b0110: // Rotate left
           ALU_Result = {A[6:0],A[7]};
        4'b0111: // Rotate right
           ALU_Result = {A[0],A[7:1]};
        4'b1000: //  Logical and 
           ALU_Result = A & B;
        4'b1001: //  Logical or
           ALU_Result = A | B;
        4'b1010: //  Logical xor 
           ALU_Result = A ^ B;
        4'b1011: //  Logical nor
           ALU_Result = ~(A | B);
        4'b1100: // Logical nand 
           ALU_Result = ~(A & B);
        4'b1101: // Logical xnor
           ALU_Result = ~(A ^ B);
        4'b1110: // Greater comparison
           ALU_Result = (A>B)?8'd1:8'd0 ;
        4'b1111: // Equal comparison   
            ALU_Result = (A==B)? 8'd1:8'd0 ;
          default: ALU_Result = A + B ; 
        endcase
    end
    assign ALU_Out = ALU_Result; // ALU out

endmodule

ALU_32bit/alu_32bit_tb.v
// ALU testbench
`timescale 1ns / 1ps  

module alu_tb;
//Inputs
 reg[31:0] A,B;
 reg[3:0] ALU_Sel;
 reg clk;

//Outputs
 wire[31:0] ALU_Out;
 wire CarryOut;
 // Verilog code for ALU
 integer i;
 alu test_unit(
            clk,
            A,B,  // ALU 8-bit Inputs                 
            ALU_Sel,// ALU Selection
            ALU_Out, // ALU 8-bit Output
            CarryOut // Carry Out Flag
     );
initial begin
    clk=0;
    forever #10 clk = ~clk;  
end 
initial begin
    $dumpfile("alu_tb.vcd");
    $dumpvars(0,alu_tb);
// hold reset state for 100 ns.
    A = 32'hAE21;
    B = 32'h25F0;
    ALU_Sel = 4'hF;
    
    for (i=0;i<=15;i=i+1)
    begin
    ALU_Sel = ALU_Sel + 4'h1;
    #20;
    end;
    $finish; 
end

endmodule

ALU_32bit/alu_tb.vcd
$date
	Fri Mar 17 01:43:43 2023
$end
$version
	Icarus Verilog
$end
$timescale
	1ps
$end
$scope module alu_tb $end
$var wire 1 ! CarryOut $end
$var wire 32 " ALU_Out [31:0] $end
$var reg 32 # A [31:0] $end
$var reg 4 $ ALU_Sel [3:0] $end
$var reg 32 % B [31:0] $end
$var reg 1 & clk $end
$var integer 32 ' i [31:0] $end
$scope module test_unit $end
$var wire 32 ( A [31:0] $end
$var wire 32 ) ALU_Out [31:0] $end
$var wire 4 * ALU_Sel [3:0] $end
$var wire 32 + B [31:0] $end
$var wire 1 & clk $end
$var wire 33 , tmp [32:0] $end
$var wire 1 ! CarryOut $end
$var reg 32 - ALU_Result [31:0] $end
$upscope $end
$upscope $end
$enddefinitions $end
$comment Show the parameter values. $end
$dumpall
$end
#0
$dumpvars
bx -
b1101010000010001 ,
b10010111110000 +
b0 *
bx )
b1010111000100001 (
b0 '
0&
b10010111110000 %
b0 $
b1010111000100001 #
bx "
0!
$end
#10000
b1101010000010001 "
b1101010000010001 )
b1101010000010001 -
1&
#20000
0&
b1 $
b1 *
b1 '
#30000
b1000100000110001 "
b1000100000110001 )
b1000100000110001 -
1&
#40000
0&
b10 $
b10 *
b10 '
#50000
b11001110011100000001111110000 "
b11001110011100000001111110000 )
b11001110011100000001111110000 -
1&
#60000
0&
b11 $
b11 *
b11 '
#70000
b100 "
b100 )
b100 -
1&
#80000
0&
b100 $
b100 *
b100 '
#90000
b10101110001000010 "
b10101110001000010 )
b10101110001000010 -
1&
#100000
0&
b101 $
b101 *
b101 '
#110000
b101011100010000 "
b101011100010000 )
b101011100010000 -
1&
#120000
0&
b110 $
b110 *
b110 '
#130000
b1000010 "
b1000010 )
b1000010 -
1&
#140000
0&
b111 $
b111 *
b111 '
#150000
b10010000 "
b10010000 )
b10010000 -
1&
#160000
0&
b1000 $
b1000 *
b1000 '
#170000
b10010000100000 "
b10010000100000 )
b10010000100000 -
1&
#180000
0&
b1001 $
b1001 *
b1001 '
#190000
b1010111111110001 "
b1010111111110001 )
b1010111111110001 -
1&
#200000
0&
b1010 $
b1010 *
b1010 '
#210000
b1000101111010001 "
b1000101111010001 )
b1000101111010001 -
1&
#220000
0&
b1011 $
b1011 *
b1011 '
#230000
b11111111111111110101000000001110 "
b11111111111111110101000000001110 )
b11111111111111110101000000001110 -
1&
#240000
0&
b1100 $
b1100 *
b1100 '
#250000
b11111111111111111101101111011111 "
b11111111111111111101101111011111 )
b11111111111111111101101111011111 -
1&
#260000
0&
b1101 $
b1101 *
b1101 '
#270000
b11111111111111110111010000101110 "
b11111111111111110111010000101110 )
b11111111111111110111010000101110 -
1&
#280000
0&
b1110 $
b1110 *
b1110 '
#290000
b1 "
b1 )
b1 -
1&
#300000
0&
b1111 $
b1111 *
b1111 '
#310000
b0 "
b0 )
b0 -
1&
#320000
0&
b10000 '
