Memory_usage/memory.v
// Verilog code to create RAM block and load data from file

`timescale 1ns/1ps

module memory(clk, en, mem_addr, mem_read_data, mem_write_data, mem_write);

    parameter WIDTH = 8; // RAM word size
    parameter DEPTH = 16; // RAM locations

    input clk, en, mem_write;
    input [WIDTH-1:0] mem_write_data;
    input [DEPTH-1:0] mem_addr;
    output [WIDTH-1:0] mem_read_data;

    integer i;

    reg [WIDTH-1:0] ram_block [0:DEPTH-1];
    reg [7:0] mem_data;
    initial begin
        for(i=0;i<DEPTH;i=i+1) begin
            ram_block[i] = {WIDTH{1'b0}};
        end

        $display("Initialised memory block");

        $readmemb("ram_data.dat",ram_block);
        $display("Memory block loaded");

        for(i=0;i<DEPTH;i=i+1) begin
            $display("%d : %b",i,ram_block[i]); 
        end
    end

    always @(posedge clk) begin
        if(en) begin
            if(mem_write)
                ram_block[mem_addr] <= mem_write_data;
            else mem_data <= ram_block[mem_addr];
        end
    end
    assign mem_read_data = mem_data;

endmodule

Memory_usage/memory_tb.v
// Testbench for instantiating RAM block

`timescale 1ns/1ps

module memory_tb();
    parameter finishtime = 500;
    parameter WIDTH = 8;
    parameter DEPTH = 4;

    reg clk, en, mem_write;
    reg [DEPTH-1:0] mem_addr;
    wire [WIDTH-1:0] mem_read_data;
    reg [WIDTH-1:0] mem_write_data;

    integer i;
    memory dut(
        .clk (clk),
        .en (en),
        .mem_write(mem_write),
        .mem_read_data (mem_read_data),
        .mem_addr (mem_addr),
        .mem_write_data (mem_write_data)
    );

    initial begin
        $dumpfile("dumpfile.vcd");
        $dumpvars(0, memory_tb);
        $monitor("WRITE %b : %b",mem_addr,mem_write_data);
        // $monitor("READ %b : %b",mem_addr,mem_read_data);
        #finishtime $finish;
    end

    initial begin
        en = 1'b0;
        mem_write = 1'b0;
        clk = 1'b0;
        mem_addr = {WIDTH{1'b0}};
        mem_write_data = {WIDTH{1'b0}};
        forever #10 clk = ~clk;
    end

    initial begin
        en = 1'b1;
        mem_write = 1'b1;
        for(i=0;i<10;i=i+1) begin
            mem_addr <= $random;
            mem_write_data <= $random;
            #20;
        end
        mem_write = 1'b0;
        for(i=0;i<10;i=i+1) begin
            mem_addr <= $random;
            #20;
        end
    end
endmodule

Memory_usage/dumpfile.vcd
$date
	Thu Apr 20 18:05:16 2023
$end
$version
	Icarus Verilog
$end
$timescale
	1ps
$end
$scope module memory_tb $end
$var wire 8 ! mem_read_data [7:0] $end
$var parameter 32 " DEPTH $end
$var parameter 32 # WIDTH $end
$var parameter 32 $ finishtime $end
$var reg 1 % clk $end
$var reg 1 & en $end
$var reg 4 ' mem_addr [3:0] $end
$var reg 1 ( mem_write $end
$var reg 8 ) mem_write_data [7:0] $end
$var integer 32 * i [31:0] $end
$scope module dut $end
$var wire 1 % clk $end
$var wire 1 & en $end
$var wire 16 + mem_addr [15:0] $end
$var wire 8 , mem_read_data [7:0] $end
$var wire 1 ( mem_write $end
$var wire 8 - mem_write_data [7:0] $end
$var parameter 32 . DEPTH $end
$var parameter 32 / WIDTH $end
$var reg 8 0 mem_data [7:0] $end
$var integer 32 1 i [31:0] $end
$upscope $end
$upscope $end
$enddefinitions $end
$comment Show the parameter values. $end
$dumpall
b1000 /
b10000 .
b111110100 $
b1000 #
b100 "
$end
#0
$dumpvars
b10000 1
bx 0
b10000001 -
bx ,
b100 +
b0 *
b10000001 )
1(
b100 '
1&
0%
bx !
$end
#10000
1%
#20000
b1100011 )
b1100011 -
b1001 +
b1001 '
0%
b1 *
#30000
1%
#40000
b10001101 )
b10001101 -
b1101 +
b1101 '
0%
b10 *
#50000
1%
#60000
b10010 )
b10010 -
b101 +
b101 '
0%
b11 *
#70000
1%
#80000
b1101 )
b1101 -
b1 +
b1 '
0%
b100 *
#90000
1%
#100000
b111101 )
b111101 -
b110 +
b110 '
0%
b101 *
#110000
1%
#120000
b10001100 )
b10001100 -
b1101 +
b1101 '
0%
b110 *
#130000
1%
#140000
b11000110 )
b11000110 -
b1001 +
b1001 '
0%
b111 *
#150000
1%
#160000
b10101010 )
b10101010 -
b101 +
b101 '
0%
b1000 *
#170000
1%
#180000
b1110111 )
b1110111 -
0%
b1001 *
#190000
1%
#200000
b10 +
b10 '
0%
0(
b0 *
#210000
b10101101 !
b10101101 ,
b10101101 0
1%
#220000
b1111 +
b1111 '
0%
b1 *
#230000
1%
#240000
b10 +
b10 '
0%
b10 *
#250000
1%
#260000
b1110 +
b1110 '
0%
b11 *
#270000
1%
#280000
b1000 +
b1000 '
0%
b100 *
#290000
1%
#300000
b101 +
b101 '
0%
b101 *
#310000
b1110111 !
b1110111 ,
b1110111 0
1%
#320000
b1100 +
b1100 '
0%
b110 *
#330000
b10101101 !
b10101101 ,
b10101101 0
1%
#340000
b1101 +
b1101 '
0%
b111 *
#350000
b10001100 !
b10001100 ,
b10001100 0
1%
#360000
0%
b1000 *
#370000
1%
#380000
b101 +
b101 '
0%
b1001 *
#390000
b1110111 !
b1110111 ,
b1110111 0
1%
#400000
0%
b1010 *
